PyFLOSIC2-2.0.0rc0.data/scripts/pyflosic2
pyflosic2/__init__.py
pyflosic2/atoms/__init__.py
pyflosic2/atoms/atoms.py
pyflosic2/atoms/bondorder.py
pyflosic2/atoms/bonds.py
pyflosic2/atoms/clean.py
pyflosic2/atoms/mmtypes.py
pyflosic2/ff/__init__.py
pyflosic2/ff/uff.py
pyflosic2/ff/uff_bonds.py
pyflosic2/ff/uff_params.py
pyflosic2/ff/uff_systems.py
pyflosic2/guess/__init__.py
pyflosic2/guess/bench_perception.py
pyflosic2/guess/clean.py
pyflosic2/guess/perception_start.py
pyflosic2/guess/pycom.py
pyflosic2/guess/pyfodmc.py
pyflosic2/guess/pyperception.py
pyflosic2/guess/perception/DFS.py
pyflosic2/guess/perception/__init__.py
pyflosic2/guess/perception/aromatic_perception.py
pyflosic2/guess/perception/atoms_perception.py
pyflosic2/guess/perception/bonds_motifs.py
pyflosic2/guess/perception/bonds_perception.py
pyflosic2/guess/perception/core_motifs.py
pyflosic2/guess/perception/electron_perception.py
pyflosic2/guess/perception/functional_groups_perception.py
pyflosic2/guess/perception/lone_motifs.py
pyflosic2/guess/perception/magic_bonds.py
pyflosic2/guess/perception/params.py
pyflosic2/guess/perception/utils.py
pyflosic2/gui/__init__.py
pyflosic2/gui/clean.py
pyflosic2/gui/view.py
pyflosic2/io/__init__.py
pyflosic2/io/flosic_io.py
pyflosic2/io/rflosic_io.py
pyflosic2/io/uflosic_io.py
pyflosic2/log/__init__.py
pyflosic2/log/clean.py
pyflosic2/log/logger.py
pyflosic2/parameters/__init__.py
pyflosic2/parameters/clean.py
pyflosic2/parameters/flosic_parameters.py
pyflosic2/sic/__init__.py
pyflosic2/sic/clean.py
pyflosic2/sic/flo.py
pyflosic2/sic/flosic.py
pyflosic2/sic/properties.py
pyflosic2/sic/rflo.py
pyflosic2/sic/rflosic.py
pyflosic2/sic/rrun.py
pyflosic2/sic/run.py
pyflosic2/sic/rworkflow.py
pyflosic2/sic/uensemble.py
pyflosic2/sic/uflo.py
pyflosic2/sic/uflosic.py
pyflosic2/sic/urun.py
pyflosic2/sic/uworkflow.py
pyflosic2/sic/workflow.py
pyflosic2/src_old/__init__.py
pyflosic2/src_old/ase_pyflosic_calculator.py
pyflosic2/src_old/ase_pyflosic_optimizer.py
PyFLOSIC2-2.0.0rc0.dist-info/LICENSE
PyFLOSIC2-2.0.0rc0.dist-info/METADATA
PyFLOSIC2-2.0.0rc0.dist-info/WHEEL
PyFLOSIC2-2.0.0rc0.dist-info/top_level.txt
PyFLOSIC2-2.0.0rc0.dist-info/RECORD
