Metadata-Version: 2.1
Name: PyFLOSIC2
Version: 2.0.0rc0
Summary: Python-based Fermi-Löwdin orbital self-interaction correction (FLO-SIC)
Home-page: https://gitlab.com/opensic/pyflosic2
Author: Sebastian Schwalbe
Author-email: theonov13@gmail.com
License: APACHE2.0
Platform: UNKNOWN
Requires-Python: >=3.6
Requires-Dist: numpy
Requires-Dist: fodMC
Requires-Dist: pyscf (==1.7.6.post1)
Requires-Dist: ase
Requires-Dist: distro
Requires-Dist: scipy
Requires-Dist: glfw (==2.1.0)
Requires-Dist: gr
Requires-Dist: PyOpenGL (==3.1.5)
Requires-Dist: h5py
